humblepy/__init__.py
humblepy/choices.py
humblepy/data/__init__.py
humblepy/data/ipfs.toml
humblepy/models/__init__.py
humblepy/models/arc3.py
humblepy/models/asa.py
humblepy/models/asset_params.py
humblepy/types/__init__.py
humblepy/types/annotated.py
humblepy/utils/__init__.py
humblepy/utils/hash.py
humblepy/utils/read.py
humblepy/utils/url.py
humblepy/utils/validate.py
humblepy-0.6.2.dist-info/LICENSE
humblepy-0.6.2.dist-info/METADATA
humblepy-0.6.2.dist-info/WHEEL
humblepy-0.6.2.dist-info/entry_points.txt
humblepy-0.6.2.dist-info/RECORD
