Metadata-Version: 2.1
Name: humblepy
Version: 0.6.2
Summary: A type-safe Python library for interacting with assets on Algorand.
Home-page: https://github.com/code-alexander/humblepy
License: Apache Software License 2.0
Author: humblepy
Author-email: alexandercodes@proton.me
Requires-Python: >=3.11,<4.0
Classifier: Development Status :: 3 - Alpha
Classifier: Intended Audience :: Developers
Classifier: License :: OSI Approved :: Apache Software License
Classifier: License :: Other/Proprietary License
Classifier: Operating System :: OS Independent
Classifier: Programming Language :: Python :: 3
Classifier: Programming Language :: Python :: 3.11
Classifier: Programming Language :: Python :: 3.12
Classifier: Topic :: Software Development :: Libraries :: Python Modules
Requires-Dist: babel (>=2.14.0,<3.0.0)
Requires-Dist: cytoolz (>=0.12.2,<0.13.0)
Requires-Dist: py-algorand-sdk (>=2.5.0,<3.0.0)
Requires-Dist: pydantic (>=2.5.3,<3.0.0)
Requires-Dist: rich (>=13.7.0,<14.0.0)
Requires-Dist: typer[all] (>=0.9.0,<0.10.0)
Project-URL: Repository, https://github.com/code-alexander/humblepy
